{"name":"develop","namedChunkGroups":{"commons":{"name":"commons","assets":[{"name":"framework.js","size":4307128},{"name":"commons.css","size":20791},{"name":"commons.js","size":3012090}],"filteredAssets":0,"assetsSize":7340009,"filteredAuxiliaryAssets":0,"auxiliaryAssetsSize":0},"component---cache-dev-404-page-js":{"name":"component---cache-dev-404-page-js","assets":[{"name":"component---cache-dev-404-page-js.js","size":71943}],"filteredAssets":0,"assetsSize":71943,"filteredAuxiliaryAssets":0,"auxiliaryAssetsSize":0},"component---src-pages-404-tsx":{"name":"component---src-pages-404-tsx","assets":[{"name":"framework.js","size":4307128},{"name":"commons.css","size":20791},{"name":"commons.js","size":3012090},{"name":"component---src-pages-404-tsx.js","size":1464568}],"filteredAssets":0,"assetsSize":8804577,"filteredAuxiliaryAssets":0,"auxiliaryAssetsSize":0},"component---src-pages-about-tsx":{"name":"component---src-pages-about-tsx","assets":[{"name":"framework.js","size":4307128},{"name":"commons.css","size":20791},{"name":"commons.js","size":3012090},{"name":"component---src-pages-about-tsx.js","size":2406973}],"filteredAssets":0,"assetsSize":9746982,"filteredAuxiliaryAssets":2,"auxiliaryAssetsSize":167164},"component---src-pages-guestbook-tsx":{"name":"component---src-pages-guestbook-tsx","assets":[{"name":"framework.js","size":4307128},{"name":"commons.css","size":20791},{"name":"commons.js","size":3012090},{"name":"component---src-pages-guestbook-tsx.js","size":1615432}],"filteredAssets":0,"assetsSize":8955441,"filteredAuxiliaryAssets":0,"auxiliaryAssetsSize":0},"component---src-pages-index-tsx":{"name":"component---src-pages-index-tsx","assets":[{"name":"framework.js","size":4307128},{"name":"commons.css","size":20791},{"name":"commons.js","size":3012090},{"name":"component---src-pages-index-tsx.js","size":2384814}],"filteredAssets":0,"assetsSize":9724823,"filteredAuxiliaryAssets":2,"auxiliaryAssetsSize":167164},"component---src-pages-playground-tsx":{"name":"component---src-pages-playground-tsx","assets":[{"name":"framework.js","size":4307128},{"name":"commons.css","size":20791},{"name":"commons.js","size":3012090},{"name":"component---src-pages-playground-tsx.js","size":1765395}],"filteredAssets":0,"assetsSize":9105404,"filteredAuxiliaryAssets":0,"auxiliaryAssetsSize":0},"component---src-templates-post-template-index-tsx":{"name":"component---src-templates-post-template-index-tsx","assets":[{"name":"framework.js","size":4307128},{"name":"commons.css","size":20791},{"name":"commons.js","size":3012090},{"name":"component---src-templates-post-template-index-tsx.js","size":2256869}],"filteredAssets":0,"assetsSize":9596878,"filteredAuxiliaryAssets":2,"auxiliaryAssetsSize":167164},"component---src-templates-posts-template-index-tsx":{"name":"component---src-templates-posts-template-index-tsx","assets":[{"name":"framework.js","size":4307128},{"name":"commons.css","size":20791},{"name":"commons.js","size":3012090},{"name":"component---src-templates-posts-template-index-tsx.js","size":1670523}],"filteredAssets":0,"assetsSize":9010532,"filteredAuxiliaryAssets":0,"auxiliaryAssetsSize":0},"component---cache-dev-404-page-jshead":{"name":"component---cache-dev-404-page-jshead","assets":[{"name":"component---cache-dev-404-page-jshead.js","size":71790}],"filteredAssets":0,"assetsSize":71790,"filteredAuxiliaryAssets":0,"auxiliaryAssetsSize":0},"component---src-pages-404-tsxhead":{"name":"component---src-pages-404-tsxhead","assets":[{"name":"framework.js","size":4307128},{"name":"commons.css","size":20791},{"name":"commons.js","size":3012090},{"name":"component---src-pages-404-tsxhead.js","size":1592533}],"filteredAssets":0,"assetsSize":8932542,"filteredAuxiliaryAssets":0,"auxiliaryAssetsSize":0},"component---src-pages-about-tsxhead":{"name":"component---src-pages-about-tsxhead","assets":[{"name":"framework.js","size":4307128},{"name":"commons.css","size":20791},{"name":"commons.js","size":3012090},{"name":"component---src-pages-about-tsxhead.js","size":2406837}],"filteredAssets":0,"assetsSize":9746846,"filteredAuxiliaryAssets":2,"auxiliaryAssetsSize":167164},"component---src-pages-guestbook-tsxhead":{"name":"component---src-pages-guestbook-tsxhead","assets":[{"name":"framework.js","size":4307128},{"name":"commons.css","size":20791},{"name":"commons.js","size":3012090},{"name":"component---src-pages-guestbook-tsxhead.js","size":1615292}],"filteredAssets":0,"assetsSize":8955301,"filteredAuxiliaryAssets":0,"auxiliaryAssetsSize":0},"component---src-pages-index-tsxhead":{"name":"component---src-pages-index-tsxhead","assets":[{"name":"framework.js","size":4307128},{"name":"commons.css","size":20791},{"name":"commons.js","size":3012090},{"name":"component---src-pages-index-tsxhead.js","size":2384679}],"filteredAssets":0,"assetsSize":9724688,"filteredAuxiliaryAssets":2,"auxiliaryAssetsSize":167164},"component---src-pages-playground-tsxhead":{"name":"component---src-pages-playground-tsxhead","assets":[{"name":"framework.js","size":4307128},{"name":"commons.css","size":20791},{"name":"commons.js","size":3012090},{"name":"component---src-pages-playground-tsxhead.js","size":1765250}],"filteredAssets":0,"assetsSize":9105259,"filteredAuxiliaryAssets":0,"auxiliaryAssetsSize":0},"component---src-templates-post-template-index-tsxhead":{"name":"component---src-templates-post-template-index-tsxhead","assets":[{"name":"framework.js","size":4307128},{"name":"commons.css","size":20791},{"name":"commons.js","size":3012090},{"name":"component---src-templates-post-template-index-tsxhead.js","size":2256722}],"filteredAssets":0,"assetsSize":9596731,"filteredAuxiliaryAssets":2,"auxiliaryAssetsSize":167164},"component---src-templates-posts-template-index-tsxhead":{"name":"component---src-templates-posts-template-index-tsxhead","assets":[{"name":"framework.js","size":4307128},{"name":"commons.css","size":20791},{"name":"commons.js","size":3012090},{"name":"component---src-templates-posts-template-index-tsxhead.js","size":1670418}],"filteredAssets":0,"assetsSize":9010427,"filteredAuxiliaryAssets":0,"auxiliaryAssetsSize":0}},"assetsByChunkName":{"commons":["framework.js","commons.css","commons.js"],"component---cache-dev-404-page-js":["component---cache-dev-404-page-js.js"],"component---src-pages-404-tsx":["framework.js","commons.css","commons.js","component---src-pages-404-tsx.js"],"component---src-pages-about-tsx":["framework.js","commons.css","commons.js","component---src-pages-about-tsx.js"],"component---src-pages-guestbook-tsx":["framework.js","commons.css","commons.js","component---src-pages-guestbook-tsx.js"],"component---src-pages-index-tsx":["framework.js","commons.css","commons.js","component---src-pages-index-tsx.js"],"component---src-pages-playground-tsx":["framework.js","commons.css","commons.js","component---src-pages-playground-tsx.js"],"component---src-templates-post-template-index-tsx":["framework.js","commons.css","commons.js","component---src-templates-post-template-index-tsx.js"],"component---src-templates-posts-template-index-tsx":["framework.js","commons.css","commons.js","component---src-templates-posts-template-index-tsx.js"],"component---cache-dev-404-page-jshead":["component---cache-dev-404-page-jshead.js"],"component---src-pages-404-tsxhead":["framework.js","commons.css","commons.js","component---src-pages-404-tsxhead.js"],"component---src-pages-about-tsxhead":["framework.js","commons.css","commons.js","component---src-pages-about-tsxhead.js"],"component---src-pages-guestbook-tsxhead":["framework.js","commons.css","commons.js","component---src-pages-guestbook-tsxhead.js"],"component---src-pages-index-tsxhead":["framework.js","commons.css","commons.js","component---src-pages-index-tsxhead.js"],"component---src-pages-playground-tsxhead":["framework.js","commons.css","commons.js","component---src-pages-playground-tsxhead.js"],"component---src-templates-post-template-index-tsxhead":["framework.js","commons.css","commons.js","component---src-templates-post-template-index-tsxhead.js"],"component---src-templates-posts-template-index-tsxhead":["framework.js","commons.css","commons.js","component---src-templates-posts-template-index-tsxhead.js"]},"childAssetsByChunkName":{}}