{"name":"develop","namedChunkGroups":{"commons":{"name":"commons","assets":[{"name":"framework.js","size":4306972},{"name":"commons.css","size":20791},{"name":"commons.js","size":3007950},{"name":"commons.c7353426bf38ebb5a09d.hot-update.js","size":876}],"filteredAssets":0,"assetsSize":7336589,"filteredAuxiliaryAssets":0,"auxiliaryAssetsSize":0},"component---cache-dev-404-page-js":{"name":"component---cache-dev-404-page-js","assets":[{"name":"component---cache-dev-404-page-js.js","size":71867}],"filteredAssets":0,"assetsSize":71867,"filteredAuxiliaryAssets":0,"auxiliaryAssetsSize":0},"component---src-pages-404-tsx":{"name":"component---src-pages-404-tsx","assets":[{"name":"framework.js","size":4306972},{"name":"commons.css","size":20791},{"name":"commons.js","size":3007950},{"name":"commons.c7353426bf38ebb5a09d.hot-update.js","size":876},{"name":"component---src-pages-404-tsx.js","size":1464342}],"filteredAssets":0,"assetsSize":8800931,"filteredAuxiliaryAssets":0,"auxiliaryAssetsSize":0},"component---src-pages-about-tsx":{"name":"component---src-pages-about-tsx","assets":[{"name":"framework.js","size":4306972},{"name":"commons.css","size":20791},{"name":"commons.js","size":3007950},{"name":"commons.c7353426bf38ebb5a09d.hot-update.js","size":876},{"name":"component---src-pages-about-tsx.js","size":2404850}],"filteredAssets":0,"assetsSize":9741439,"filteredAuxiliaryAssets":2,"auxiliaryAssetsSize":167164},"component---src-pages-guestbook-tsx":{"name":"component---src-pages-guestbook-tsx","assets":[{"name":"framework.js","size":4306972},{"name":"commons.css","size":20791},{"name":"commons.js","size":3007950},{"name":"commons.c7353426bf38ebb5a09d.hot-update.js","size":876},{"name":"component---src-pages-guestbook-tsx.js","size":1615042}],"filteredAssets":0,"assetsSize":8951631,"filteredAuxiliaryAssets":0,"auxiliaryAssetsSize":0},"component---src-pages-index-tsx":{"name":"component---src-pages-index-tsx","assets":[{"name":"framework.js","size":4306972},{"name":"commons.css","size":20791},{"name":"commons.js","size":3007950},{"name":"commons.c7353426bf38ebb5a09d.hot-update.js","size":876},{"name":"component---src-pages-index-tsx.js","size":2383325},{"name":"component---src-pages-index-tsx.c7353426bf38ebb5a09d.hot-update.js","size":10313}],"filteredAssets":0,"assetsSize":9730227,"filteredAuxiliaryAssets":2,"auxiliaryAssetsSize":167164},"component---src-pages-playground-tsx":{"name":"component---src-pages-playground-tsx","assets":[{"name":"framework.js","size":4306972},{"name":"commons.css","size":20791},{"name":"commons.js","size":3007950},{"name":"commons.c7353426bf38ebb5a09d.hot-update.js","size":876},{"name":"component---src-pages-playground-tsx.js","size":1764829}],"filteredAssets":0,"assetsSize":9101418,"filteredAuxiliaryAssets":0,"auxiliaryAssetsSize":0},"component---src-templates-post-template-index-tsx":{"name":"component---src-templates-post-template-index-tsx","assets":[{"name":"framework.js","size":4306972},{"name":"commons.css","size":20791},{"name":"commons.js","size":3007950},{"name":"commons.c7353426bf38ebb5a09d.hot-update.js","size":876},{"name":"component---src-templates-post-template-index-tsx.js","size":2255476}],"filteredAssets":0,"assetsSize":9592065,"filteredAuxiliaryAssets":2,"auxiliaryAssetsSize":167164},"component---src-templates-posts-template-index-tsx":{"name":"component---src-templates-posts-template-index-tsx","assets":[{"name":"framework.js","size":4306972},{"name":"commons.css","size":20791},{"name":"commons.js","size":3007950},{"name":"commons.c7353426bf38ebb5a09d.hot-update.js","size":876},{"name":"component---src-templates-posts-template-index-tsx.js","size":1669869}],"filteredAssets":0,"assetsSize":9006458,"filteredAuxiliaryAssets":0,"auxiliaryAssetsSize":0},"component---cache-dev-404-page-jshead":{"name":"component---cache-dev-404-page-jshead","assets":[{"name":"component---cache-dev-404-page-jshead.js","size":71710}],"filteredAssets":0,"assetsSize":71710,"filteredAuxiliaryAssets":0,"auxiliaryAssetsSize":0},"component---src-pages-404-tsxhead":{"name":"component---src-pages-404-tsxhead","assets":[{"name":"framework.js","size":4306972},{"name":"commons.css","size":20791},{"name":"commons.js","size":3007950},{"name":"commons.c7353426bf38ebb5a09d.hot-update.js","size":876},{"name":"component---src-pages-404-tsxhead.js","size":1592251}],"filteredAssets":0,"assetsSize":8928840,"filteredAuxiliaryAssets":0,"auxiliaryAssetsSize":0},"component---src-pages-about-tsxhead":{"name":"component---src-pages-about-tsxhead","assets":[{"name":"framework.js","size":4306972},{"name":"commons.css","size":20791},{"name":"commons.js","size":3007950},{"name":"commons.c7353426bf38ebb5a09d.hot-update.js","size":876},{"name":"component---src-pages-about-tsxhead.js","size":2404714}],"filteredAssets":0,"assetsSize":9741303,"filteredAuxiliaryAssets":2,"auxiliaryAssetsSize":167164},"component---src-pages-guestbook-tsxhead":{"name":"component---src-pages-guestbook-tsxhead","assets":[{"name":"framework.js","size":4306972},{"name":"commons.css","size":20791},{"name":"commons.js","size":3007950},{"name":"commons.c7353426bf38ebb5a09d.hot-update.js","size":876},{"name":"component---src-pages-guestbook-tsxhead.js","size":1614902}],"filteredAssets":0,"assetsSize":8951491,"filteredAuxiliaryAssets":0,"auxiliaryAssetsSize":0},"component---src-pages-index-tsxhead":{"name":"component---src-pages-index-tsxhead","assets":[{"name":"framework.js","size":4306972},{"name":"commons.css","size":20791},{"name":"commons.js","size":3007950},{"name":"commons.c7353426bf38ebb5a09d.hot-update.js","size":876},{"name":"component---src-pages-index-tsxhead.js","size":2383190},{"name":"component---src-pages-index-tsxhead.c7353426bf38ebb5a09d.hot-update.js","size":10178}],"filteredAssets":0,"assetsSize":9729957,"filteredAuxiliaryAssets":2,"auxiliaryAssetsSize":167164},"component---src-pages-playground-tsxhead":{"name":"component---src-pages-playground-tsxhead","assets":[{"name":"framework.js","size":4306972},{"name":"commons.css","size":20791},{"name":"commons.js","size":3007950},{"name":"commons.c7353426bf38ebb5a09d.hot-update.js","size":876},{"name":"component---src-pages-playground-tsxhead.js","size":1764688}],"filteredAssets":0,"assetsSize":9101277,"filteredAuxiliaryAssets":0,"auxiliaryAssetsSize":0},"component---src-templates-post-template-index-tsxhead":{"name":"component---src-templates-post-template-index-tsxhead","assets":[{"name":"framework.js","size":4306972},{"name":"commons.css","size":20791},{"name":"commons.js","size":3007950},{"name":"commons.c7353426bf38ebb5a09d.hot-update.js","size":876},{"name":"component---src-templates-post-template-index-tsxhead.js","size":2255333}],"filteredAssets":0,"assetsSize":9591922,"filteredAuxiliaryAssets":2,"auxiliaryAssetsSize":167164},"component---src-templates-posts-template-index-tsxhead":{"name":"component---src-templates-posts-template-index-tsxhead","assets":[{"name":"framework.js","size":4306972},{"name":"commons.css","size":20791},{"name":"commons.js","size":3007950},{"name":"commons.c7353426bf38ebb5a09d.hot-update.js","size":876},{"name":"component---src-templates-posts-template-index-tsxhead.js","size":1669764}],"filteredAssets":0,"assetsSize":9006353,"filteredAuxiliaryAssets":0,"auxiliaryAssetsSize":0}},"assetsByChunkName":{"commons":["framework.js","commons.css","commons.js","commons.c7353426bf38ebb5a09d.hot-update.js"],"component---cache-dev-404-page-js":["component---cache-dev-404-page-js.js"],"component---src-pages-404-tsx":["framework.js","commons.css","commons.js","commons.c7353426bf38ebb5a09d.hot-update.js","component---src-pages-404-tsx.js"],"component---src-pages-about-tsx":["framework.js","commons.css","commons.js","commons.c7353426bf38ebb5a09d.hot-update.js","component---src-pages-about-tsx.js"],"component---src-pages-guestbook-tsx":["framework.js","commons.css","commons.js","commons.c7353426bf38ebb5a09d.hot-update.js","component---src-pages-guestbook-tsx.js"],"component---src-pages-index-tsx":["framework.js","commons.css","commons.js","commons.c7353426bf38ebb5a09d.hot-update.js","component---src-pages-index-tsx.js","component---src-pages-index-tsx.c7353426bf38ebb5a09d.hot-update.js"],"component---src-pages-playground-tsx":["framework.js","commons.css","commons.js","commons.c7353426bf38ebb5a09d.hot-update.js","component---src-pages-playground-tsx.js"],"component---src-templates-post-template-index-tsx":["framework.js","commons.css","commons.js","commons.c7353426bf38ebb5a09d.hot-update.js","component---src-templates-post-template-index-tsx.js"],"component---src-templates-posts-template-index-tsx":["framework.js","commons.css","commons.js","commons.c7353426bf38ebb5a09d.hot-update.js","component---src-templates-posts-template-index-tsx.js"],"component---cache-dev-404-page-jshead":["component---cache-dev-404-page-jshead.js"],"component---src-pages-404-tsxhead":["framework.js","commons.css","commons.js","commons.c7353426bf38ebb5a09d.hot-update.js","component---src-pages-404-tsxhead.js"],"component---src-pages-about-tsxhead":["framework.js","commons.css","commons.js","commons.c7353426bf38ebb5a09d.hot-update.js","component---src-pages-about-tsxhead.js"],"component---src-pages-guestbook-tsxhead":["framework.js","commons.css","commons.js","commons.c7353426bf38ebb5a09d.hot-update.js","component---src-pages-guestbook-tsxhead.js"],"component---src-pages-index-tsxhead":["framework.js","commons.css","commons.js","commons.c7353426bf38ebb5a09d.hot-update.js","component---src-pages-index-tsxhead.js","component---src-pages-index-tsxhead.c7353426bf38ebb5a09d.hot-update.js"],"component---src-pages-playground-tsxhead":["framework.js","commons.css","commons.js","commons.c7353426bf38ebb5a09d.hot-update.js","component---src-pages-playground-tsxhead.js"],"component---src-templates-post-template-index-tsxhead":["framework.js","commons.css","commons.js","commons.c7353426bf38ebb5a09d.hot-update.js","component---src-templates-post-template-index-tsxhead.js"],"component---src-templates-posts-template-index-tsxhead":["framework.js","commons.css","commons.js","commons.c7353426bf38ebb5a09d.hot-update.js","component---src-templates-posts-template-index-tsxhead.js"]},"childAssetsByChunkName":{}}